{"title":"Bartosz Wróblewski","markdown":{"yaml":{"title":"Bartosz Wróblewski","image":"images/business_profile_2.JPG","toc":true,"toc-depth":3,"toc-expand":true,"format":{"html":"default"},"about":{"template":"jolla","image-width":"20em","image-shape":"round","id":"resume","links":[{"icon":"linkedin","text":"LinkedIn","href":"https://www.linkedin.com/in/bartoszmwroblewski/"},{"icon":"github","text":"Github","href":"https://github.com/bwrob/"},{"icon":"envelope","text":"Contact","href":"mailto:bartosz.marcin.wroblewski@gmail.com"}]}},"headingText":"Quantitative Analyst \\| Software Engineer","containsRefs":false,"markdown":"\n\n::: {#resume}\n<center>\n\n\nMathematician at heart, quantitative finance technologist by trade.\nI leverage diverse experiences in academia, derivatives valuation, market risk,\nand quantitative development to bring a generalist's perspective to quantitative finance and software engineering.\n\n</center>\n:::\n\n## Professional Experience\n\n### [DXC Luxoft](https://www.luxoft.com/)\n\n#### Senior Software Developer \\| Sep 2024 -- Present\n\nRisk Engine Engineer role in the counterparty credit risk (CCR) modelling and analytics team within R&C model development group.\n\n### [Syberry](https://www.syberry.com/)\n\n#### Financial Software Engineer \\| Sep 2023 -- Sep 2024\n\nDevelopment of a [financial platform](https://www.syberry.com/case-studies/game-changing-financial-platform/) for a hedge fund client.\n\n-   Quantitative developer bridging the gap between hedge fund risk managers and software engineers.\n-   Developing risk management platform that pipes and transforms trading data.\n-   Responsible for integration of vendor risk management system into the platform, efficient orchestration of asynchronous API calls and resources.\n-   Working directly with client's risk manager and CRO on specifying the business needs and requirements.\n\n  **Technologies**\n\n-   *Backend*: Python, Dagster, FastAPI, Pytest, Pandas, NumPy, SQLAlchemy.\n-   *Databases*: PostgreSQL, DuckDB.\n-   *Infrastructure/pipelines*: Amazon Web Services, Terraform, Terraspace, Docker, GitHub Actions.\n\n### [Bank of New York Mellon](https://www.bnymellon.com/)\n\n#### Senior Specialist, Model Development \\| Jul 2022 -- Sep 2023\n\nIndependent specialist at Risk and Compliance department (MO). Market Risk team responsible for modeling of VaR and SVaR, comprehensive test scenarios and portfolio sensitivity exposures.\n\n-   Developing and maintaining market risk models --- VaR, SVaR --- and stress testing frameworks implemented in C++.\n-   Calibrating and benchmarking vendor pricing models (Murex risk management system).\n-   Designing, creating and analyzing risk-related reports and ad hoc analyses for front office and risk management.\n-   Responsible for Market Risk RWA projections submission for CCAR 2023.\n-   Coordinating development projects with IT, Validation and Risk Management.\n-   Developed a method for directly comparing interest rate sensitivities between FO and MO systems using different conventions and curves setups.\n-   Re-implemented legacy C++ volatility surface builder in Python without performance loss.\n\n**Technologies**\n\n-   *Internal risk models*: C++.\n-   *Vendor pricing system*: [Murex](https://www.murex.com/en).\n-   *Databases*: MS SQL.\n-   *Tooling*: Python, Quantlib, VBA.\n\n### [Credit Suisse](https://www.credit-suisse.com/)\n\n#### Quantitative Analyst \\| Nov 2018 -- Jun 2022\n\nJunior analyst at Credit Derivatives division, part of global front office QuantStrats department (700+ quants, developers and data analysts).\n\n-   Development and maintenance of an in-house valuation framework used across bank's systems (COM C++ and .Net). Contributions to valuation models and market data object builders used in pricing.\n-   Providing direct support to traders and Middle Office in ad hoc investigations on valuation, risks and technical issues.\n-   Extending and creating COM-addin-based Excel pricing sheets used by Trading and Product Control.\n-   Assisting with calculation and analysis of risk profiles, PnL reports, transition impact assessments of trade portfolios.\n-   Represented the company by giving lectures and taking part in campus recruitment programs.\n-   Coordinated resolution of strategic process of calculating Collateral Adjusted Valuation for the xVA desk.\n\n**Structured Notes**\n\nCredit Suisse issued structured note products (corporate bonds with derivatives attached to payout).\n\n-   Contributed to structured notes valuation model framework implemented in factorized C++.\n-   Updated credit curve models and utilities to be compatible with OIS discounting in preparation to [LIBOR cessation](https://www.forbes.com/advisor/investing/what-is-libor/) (F#).\n-   Extended trading pricing sheets with logic needed to price instruments with compounding rates financing (Excel, COM-addins, .Net extensions).\n-   Collaborated with quantitative developers from in-house risk management system project on addition of new market data builders (C#).\n\n**Longevity Derivatives**\n\nLongevity-based (insurance policies and [pension schemes](https://www.independent.co.uk/news/business/news/itv-pays-credit-suisse-to-take-on-the-risk-on-its-pension-scheme-2342304.html)) financial derivatives.\n\n-   Migrated existing legacy tools to 64-bit environment.\n-   Provided technical support to Product Control in their monthly tie-in processes.\n\n**Technologies**\n\n-   *Pricing framework*: F#, C++, COM.\n-   *Risk Managment*: C#.\n-   *Trading tools*: Excel, VBA.\n-   *CI/CD*: Perforce, TeamCity.\n\n## Academic Experience\n\n### [Wrocław University of Science and Technology](https://wmat.pwr.edu.pl/)\n\n#### Teaching Assistant \\| Oct 2024 -- Present\n\nTeaching computer science for Mathematics students.\n\n### [University of Wrocław](https://www.math.uni.wroc.pl/)\n\n#### PhD Candidate \\| Oct 2016 -- Jan 2019\n\nResearched evolution equations involving non-local unbounded operators. Focused on applications of functional and harmonic analysis. Main 'hero' of my research was the [fractional Laplacian operator](https://en.wikipedia.org/wiki/Fractional_Laplacian) --- jump-diffusion analogue of the classical Laplacian.\n\nAlso interested in hydrodynamic models and applications of PDEs in physics (porous medium modelling, flocking models, quantum mechanics).\n\n*Unfinished.*\n\n#### Junior Researcher \\| Apr 2017 -- Jan 2019\n\nParticipated in the Polish National Science Center research grant [Nonlocal parabolic problems: regularity, blowup, pattern formation](https://projekty.ncn.gov.pl/en/index.php?projekt_id=352757). Principal Investigator Prof. [Piotr Biler](http://www.math.uni.wroc.pl/~biler/).\n\n#### Teaching Assistant \\| Mar 2017 -- Jul 2018\n\nNon-linear Functional Analysis, Ordinary Differential Equations, Honors Ordinary Differential Equations.\n\n### [University of Warsaw](https://www.mimuw.edu.pl/en/studies/)\n\n#### Research Intern \\| Dec 2016 -- Mar 2017\n\nVisiting position during [CrossFields PDEs](https://crossfields.impan.pl/index.html) semester organised and sponsored by [The Simons Foundation](https://www.simonsfoundation.org/).\n\nCollaboration with Raphael Dunchin, Piotr B. Mucha and with Jan Peszek in the research on fractional Euler alignment system (hydrodynamic flocking dynamics).\n\n-   [Regular solutions to the fractional Euler alignment system in the Besov spaces framework](https://arxiv.org/abs/1804.07611) published in *Mathematical Models and Methods in Applied Sciences Vol. 29, No. 01, pp. 89-119*\n\n#### Teaching Assistant \\| Jan 2017 -- Mar 2017\n\nAnalysis 1, Analysis 2.\n\n## Education\n\n### [University of Wrocław](https://www.math.uni.wroc.pl/)\n\n#### Msc in Theoretical Mathematics \\| Oct 2014 -- Sep 2016\n\nThesis topic: *\"The anomalous diffusion and fractional Laplacian on the half-line\"* written under the supervision of Prof. [Grzegorz Karch](https://karch.math.uni.wroc.pl/).\n\n### [Wrocław University of Science and Technology](https://wmat.pwr.edu.pl)\n\n#### BSc in Theoretical Mathematics \\| Oct 2011 -- Jul 2014\n","srcMarkdownNoYaml":"\n\n::: {#resume}\n<center>\n\n##### Quantitative Analyst \\| Software Engineer\n\nMathematician at heart, quantitative finance technologist by trade.\nI leverage diverse experiences in academia, derivatives valuation, market risk,\nand quantitative development to bring a generalist's perspective to quantitative finance and software engineering.\n\n</center>\n:::\n\n## Professional Experience\n\n### [DXC Luxoft](https://www.luxoft.com/)\n\n#### Senior Software Developer \\| Sep 2024 -- Present\n\nRisk Engine Engineer role in the counterparty credit risk (CCR) modelling and analytics team within R&C model development group.\n\n### [Syberry](https://www.syberry.com/)\n\n#### Financial Software Engineer \\| Sep 2023 -- Sep 2024\n\nDevelopment of a [financial platform](https://www.syberry.com/case-studies/game-changing-financial-platform/) for a hedge fund client.\n\n-   Quantitative developer bridging the gap between hedge fund risk managers and software engineers.\n-   Developing risk management platform that pipes and transforms trading data.\n-   Responsible for integration of vendor risk management system into the platform, efficient orchestration of asynchronous API calls and resources.\n-   Working directly with client's risk manager and CRO on specifying the business needs and requirements.\n\n  **Technologies**\n\n-   *Backend*: Python, Dagster, FastAPI, Pytest, Pandas, NumPy, SQLAlchemy.\n-   *Databases*: PostgreSQL, DuckDB.\n-   *Infrastructure/pipelines*: Amazon Web Services, Terraform, Terraspace, Docker, GitHub Actions.\n\n### [Bank of New York Mellon](https://www.bnymellon.com/)\n\n#### Senior Specialist, Model Development \\| Jul 2022 -- Sep 2023\n\nIndependent specialist at Risk and Compliance department (MO). Market Risk team responsible for modeling of VaR and SVaR, comprehensive test scenarios and portfolio sensitivity exposures.\n\n-   Developing and maintaining market risk models --- VaR, SVaR --- and stress testing frameworks implemented in C++.\n-   Calibrating and benchmarking vendor pricing models (Murex risk management system).\n-   Designing, creating and analyzing risk-related reports and ad hoc analyses for front office and risk management.\n-   Responsible for Market Risk RWA projections submission for CCAR 2023.\n-   Coordinating development projects with IT, Validation and Risk Management.\n-   Developed a method for directly comparing interest rate sensitivities between FO and MO systems using different conventions and curves setups.\n-   Re-implemented legacy C++ volatility surface builder in Python without performance loss.\n\n**Technologies**\n\n-   *Internal risk models*: C++.\n-   *Vendor pricing system*: [Murex](https://www.murex.com/en).\n-   *Databases*: MS SQL.\n-   *Tooling*: Python, Quantlib, VBA.\n\n### [Credit Suisse](https://www.credit-suisse.com/)\n\n#### Quantitative Analyst \\| Nov 2018 -- Jun 2022\n\nJunior analyst at Credit Derivatives division, part of global front office QuantStrats department (700+ quants, developers and data analysts).\n\n-   Development and maintenance of an in-house valuation framework used across bank's systems (COM C++ and .Net). Contributions to valuation models and market data object builders used in pricing.\n-   Providing direct support to traders and Middle Office in ad hoc investigations on valuation, risks and technical issues.\n-   Extending and creating COM-addin-based Excel pricing sheets used by Trading and Product Control.\n-   Assisting with calculation and analysis of risk profiles, PnL reports, transition impact assessments of trade portfolios.\n-   Represented the company by giving lectures and taking part in campus recruitment programs.\n-   Coordinated resolution of strategic process of calculating Collateral Adjusted Valuation for the xVA desk.\n\n**Structured Notes**\n\nCredit Suisse issued structured note products (corporate bonds with derivatives attached to payout).\n\n-   Contributed to structured notes valuation model framework implemented in factorized C++.\n-   Updated credit curve models and utilities to be compatible with OIS discounting in preparation to [LIBOR cessation](https://www.forbes.com/advisor/investing/what-is-libor/) (F#).\n-   Extended trading pricing sheets with logic needed to price instruments with compounding rates financing (Excel, COM-addins, .Net extensions).\n-   Collaborated with quantitative developers from in-house risk management system project on addition of new market data builders (C#).\n\n**Longevity Derivatives**\n\nLongevity-based (insurance policies and [pension schemes](https://www.independent.co.uk/news/business/news/itv-pays-credit-suisse-to-take-on-the-risk-on-its-pension-scheme-2342304.html)) financial derivatives.\n\n-   Migrated existing legacy tools to 64-bit environment.\n-   Provided technical support to Product Control in their monthly tie-in processes.\n\n**Technologies**\n\n-   *Pricing framework*: F#, C++, COM.\n-   *Risk Managment*: C#.\n-   *Trading tools*: Excel, VBA.\n-   *CI/CD*: Perforce, TeamCity.\n\n## Academic Experience\n\n### [Wrocław University of Science and Technology](https://wmat.pwr.edu.pl/)\n\n#### Teaching Assistant \\| Oct 2024 -- Present\n\nTeaching computer science for Mathematics students.\n\n### [University of Wrocław](https://www.math.uni.wroc.pl/)\n\n#### PhD Candidate \\| Oct 2016 -- Jan 2019\n\nResearched evolution equations involving non-local unbounded operators. Focused on applications of functional and harmonic analysis. Main 'hero' of my research was the [fractional Laplacian operator](https://en.wikipedia.org/wiki/Fractional_Laplacian) --- jump-diffusion analogue of the classical Laplacian.\n\nAlso interested in hydrodynamic models and applications of PDEs in physics (porous medium modelling, flocking models, quantum mechanics).\n\n*Unfinished.*\n\n#### Junior Researcher \\| Apr 2017 -- Jan 2019\n\nParticipated in the Polish National Science Center research grant [Nonlocal parabolic problems: regularity, blowup, pattern formation](https://projekty.ncn.gov.pl/en/index.php?projekt_id=352757). Principal Investigator Prof. [Piotr Biler](http://www.math.uni.wroc.pl/~biler/).\n\n#### Teaching Assistant \\| Mar 2017 -- Jul 2018\n\nNon-linear Functional Analysis, Ordinary Differential Equations, Honors Ordinary Differential Equations.\n\n### [University of Warsaw](https://www.mimuw.edu.pl/en/studies/)\n\n#### Research Intern \\| Dec 2016 -- Mar 2017\n\nVisiting position during [CrossFields PDEs](https://crossfields.impan.pl/index.html) semester organised and sponsored by [The Simons Foundation](https://www.simonsfoundation.org/).\n\nCollaboration with Raphael Dunchin, Piotr B. Mucha and with Jan Peszek in the research on fractional Euler alignment system (hydrodynamic flocking dynamics).\n\n-   [Regular solutions to the fractional Euler alignment system in the Besov spaces framework](https://arxiv.org/abs/1804.07611) published in *Mathematical Models and Methods in Applied Sciences Vol. 29, No. 01, pp. 89-119*\n\n#### Teaching Assistant \\| Jan 2017 -- Mar 2017\n\nAnalysis 1, Analysis 2.\n\n## Education\n\n### [University of Wrocław](https://www.math.uni.wroc.pl/)\n\n#### Msc in Theoretical Mathematics \\| Oct 2014 -- Sep 2016\n\nThesis topic: *\"The anomalous diffusion and fractional Laplacian on the half-line\"* written under the supervision of Prof. [Grzegorz Karch](https://karch.math.uni.wroc.pl/).\n\n### [Wrocław University of Science and Technology](https://wmat.pwr.edu.pl)\n\n#### BSc in Theoretical Mathematics \\| Oct 2011 -- Jul 2014\n"},"formats":{"html":{"identifier":{"display-name":"HTML","target-format":"html","base-format":"html"},"execute":{"fig-width":7,"fig-height":5,"fig-format":"retina","fig-dpi":96,"df-print":"default","error":false,"eval":true,"cache":null,"freeze":true,"echo":true,"output":true,"warning":true,"include":true,"keep-md":false,"keep-ipynb":false,"ipynb":null,"enabled":null,"daemon":null,"daemon-restart":false,"debug":false,"ipynb-filters":[],"ipynb-shell-interactivity":null,"plotly-connected":true,"engine":"markdown"},"render":{"keep-tex":false,"keep-typ":false,"keep-source":false,"keep-hidden":false,"prefer-html":false,"output-divs":true,"output-ext":"html","fig-align":"default","fig-pos":null,"fig-env":null,"code-fold":"none","code-overflow":"scroll","code-link":false,"code-line-numbers":true,"code-tools":false,"tbl-colwidths":"auto","merge-includes":true,"inline-includes":false,"preserve-yaml":false,"latex-auto-mk":true,"latex-auto-install":true,"latex-clean":true,"latex-min-runs":1,"latex-max-runs":10,"latex-makeindex":"makeindex","latex-makeindex-opts":[],"latex-tlmgr-opts":[],"latex-input-paths":[],"latex-output-dir":null,"link-external-icon":false,"link-external-newwindow":false,"self-contained-math":false,"format-resources":[],"notebook-links":true},"pandoc":{"standalone":true,"wrap":"none","default-image-extension":"png","to":"html","css":["../styles.css"],"toc":true,"highlight-style":"github","toc-depth":3,"output-file":"resume.html"},"language":{"toc-title-document":"Table of contents","toc-title-website":"On this page","related-formats-title":"Other Formats","related-notebooks-title":"Notebooks","source-notebooks-prefix":"Source","other-links-title":"Other Links","code-links-title":"Code Links","launch-dev-container-title":"Launch Dev Container","launch-binder-title":"Launch Binder","article-notebook-label":"Article Notebook","notebook-preview-download":"Download Notebook","notebook-preview-download-src":"Download Source","notebook-preview-back":"Back to Article","manuscript-meca-bundle":"MECA Bundle","section-title-abstract":"Abstract","section-title-appendices":"Appendices","section-title-footnotes":"Footnotes","section-title-references":"References","section-title-reuse":"Reuse","section-title-copyright":"Copyright","section-title-citation":"Citation","appendix-attribution-cite-as":"For attribution, please cite this work as:","appendix-attribution-bibtex":"BibTeX citation:","appendix-view-license":"View License","title-block-author-single":"Author","title-block-author-plural":"Authors","title-block-affiliation-single":"Affiliation","title-block-affiliation-plural":"Affiliations","title-block-published":"Published","title-block-modified":"Modified","title-block-keywords":"Keywords","callout-tip-title":"Tip","callout-note-title":"Note","callout-warning-title":"Warning","callout-important-title":"Important","callout-caution-title":"Caution","code-summary":"Code","code-tools-menu-caption":"Code","code-tools-show-all-code":"Show All Code","code-tools-hide-all-code":"Hide All Code","code-tools-view-source":"View Source","code-tools-source-code":"Source Code","tools-share":"Share","tools-download":"Download","code-line":"Line","code-lines":"Lines","copy-button-tooltip":"Copy to Clipboard","copy-button-tooltip-success":"Copied!","repo-action-links-edit":"Edit this page","repo-action-links-source":"View source","repo-action-links-issue":"Report an issue","back-to-top":"Back to top","search-no-results-text":"No results","search-matching-documents-text":"matching documents","search-copy-link-title":"Copy link to search","search-hide-matches-text":"Hide additional matches","search-more-match-text":"more match in this document","search-more-matches-text":"more matches in this document","search-clear-button-title":"Clear","search-text-placeholder":"","search-detached-cancel-button-title":"Cancel","search-submit-button-title":"Submit","search-label":"Search","toggle-section":"Toggle section","toggle-sidebar":"Toggle sidebar navigation","toggle-dark-mode":"Toggle dark mode","toggle-reader-mode":"Toggle reader mode","toggle-navigation":"Toggle navigation","crossref-fig-title":"Figure","crossref-tbl-title":"Table","crossref-lst-title":"Listing","crossref-thm-title":"Theorem","crossref-lem-title":"Lemma","crossref-cor-title":"Corollary","crossref-prp-title":"Proposition","crossref-cnj-title":"Conjecture","crossref-def-title":"Definition","crossref-exm-title":"Example","crossref-exr-title":"Exercise","crossref-ch-prefix":"Chapter","crossref-apx-prefix":"Appendix","crossref-sec-prefix":"Section","crossref-eq-prefix":"Equation","crossref-lof-title":"List of Figures","crossref-lot-title":"List of Tables","crossref-lol-title":"List of Listings","environment-proof-title":"Proof","environment-remark-title":"Remark","environment-solution-title":"Solution","listing-page-order-by":"Order By","listing-page-order-by-default":"Default","listing-page-order-by-date-asc":"Oldest","listing-page-order-by-date-desc":"Newest","listing-page-order-by-number-desc":"High to Low","listing-page-order-by-number-asc":"Low to High","listing-page-field-date":"Date","listing-page-field-title":"Title","listing-page-field-description":"Description","listing-page-field-author":"Author","listing-page-field-filename":"File Name","listing-page-field-filemodified":"Modified","listing-page-field-subtitle":"Subtitle","listing-page-field-readingtime":"Reading Time","listing-page-field-wordcount":"Word Count","listing-page-field-categories":"Categories","listing-page-minutes-compact":"{0} min","listing-page-category-all":"All","listing-page-no-matches":"No matching items","listing-page-words":"{0} words","listing-page-filter":"Filter","draft":"Draft"},"metadata":{"lang":"en","fig-responsive":true,"quarto-version":"1.5.57","theme":{"dark":["darkly","../theme-dark.scss"],"light":"flatly"},"title-block-banner":true,"code-copy":true,"code-block-border-left":true,"title":"Bartosz Wróblewski","image":"images/business_profile_2.JPG","toc-expand":true,"about":{"template":"jolla","image-width":"20em","image-shape":"round","id":"resume","links":[{"icon":"linkedin","text":"LinkedIn","href":"https://www.linkedin.com/in/bartoszmwroblewski/"},{"icon":"github","text":"Github","href":"https://github.com/bwrob/"},{"icon":"envelope","text":"Contact","href":"mailto:bartosz.marcin.wroblewski@gmail.com"}]}},"extensions":{"book":{"multiFile":true}}}},"projectFormats":["html"]}